Metadata-Version: 2.1
Name: VirtualCam
Version: 1.0.2
Summary: A model for virtual camera, including UI.
Home-page: https://github.com/myhldh/VirtualCam
Author: OscarMYH(myhldh)
Author-email: oscarmyh@163.com
License: MIT
Keywords: python,virtual camera,camera,virtual,computer vision,OscarMYH,myhldh,lightweight,windows,mac,linux
Classifier: Development Status :: 1 - Planning
Classifier: Intended Audience :: Developers
Classifier: Programming Language :: Python :: 3
Classifier: Operating System :: Unix
Classifier: Operating System :: MacOS :: MacOS X
Classifier: Operating System :: Microsoft :: Windows
License-File: LICENSE
Requires-Dist: numpy
Requires-Dist: opencv-python
Requires-Dist: Pillow
Requires-Dist: pyvirtualcam
Requires-Dist: keyboard
